opto/__init__.py
opto/version.py
opto/optimizers/__init__.py
opto/optimizers/buffers.py
opto/optimizers/opro.py
opto/optimizers/optimizer.py
opto/optimizers/optoprime.py
opto/optimizers/optoprimemulti.py
opto/optimizers/textgrad.py
opto/optimizers/utils.py
opto/trace/README.md
opto/trace/__init__.py
opto/trace/broadcast.py
opto/trace/bundle.py
opto/trace/containers.py
opto/trace/errors.py
opto/trace/iterators.py
opto/trace/modules.py
opto/trace/nodes.py
opto/trace/operators.py
opto/trace/utils.py
opto/trace/propagators/__init__.py
opto/trace/propagators/graph_propagator.py
opto/trace/propagators/propagators.py
opto/utils/__init__.py
opto/utils/llm.py
opto/utils/trainer.py
trace_opt-0.1.3.8.dist-info/LICENSE
trace_opt-0.1.3.8.dist-info/METADATA
trace_opt-0.1.3.8.dist-info/WHEEL
trace_opt-0.1.3.8.dist-info/top_level.txt
trace_opt-0.1.3.8.dist-info/RECORD
