Metadata-Version: 2.1
Name: trace-opt
Version: 0.1.3.8
Summary: An AutoDiff-like tool for training AI systems end-to-end with general feedback
Home-page: https://github.com/microsoft/trace
Author: Trace Team
Author-email: chinganc@microsoft.com
License: MIT LICENSE
Project-URL: Homepage, https://microsoft.github.io/Trace/
Project-URL: Documentation, https://microsoft.github.io/Trace/intro.html
Project-URL: Repository, https://github.com/microsoft/Trace.git
Keywords: trace,opto,AutoDiff
Classifier: Development Status :: 4 - Beta
Classifier: Intended Audience :: Developers
Classifier: License :: OSI Approved :: MIT License
Classifier: Programming Language :: Python :: 3.9
Requires-Python: >=3.9
License-File: LICENSE
Requires-Dist: graphviz>=0.20.1
Requires-Dist: scikit-learn
Requires-Dist: xgboost
Requires-Dist: litellm
Requires-Dist: black
Provides-Extra: autogen
Requires-Dist: autogen-agentchat==0.2.40; extra == "autogen"
